bpdi/__init__.py
bpdi-0.0.2.dist-info/METADATA
bpdi-0.0.2.dist-info/WHEEL
bpdi-0.0.2.dist-info/top_level.txt
bpdi-0.0.2.dist-info/RECORD
