Metadata-Version: 2.1
Name: bpdi
Version: 0.0.2
Summary: Python bpdi Package
Home-page: UNKNOWN
Author: UNKNOWN
Author-email: UNKNOWN
License: UNKNOWN
Platform: UNKNOWN
Requires-Dist: pandas
